tpot/__init__.py
tpot/_version.py
tpot/base.py
tpot/decorators.py
tpot/driver.py
tpot/export_utils.py
tpot/gp_deap.py
tpot/gp_types.py
tpot/metrics.py
tpot/operator_utils.py
tpot/tpot.py
tpot/builtins/__init__.py
tpot/builtins/combine_dfs.py
tpot/builtins/feature_transformers.py
tpot/builtins/one_hot_encoder.py
tpot/builtins/stacking_estimator.py
tpot/builtins/zero_count.py
tpot/config/__init__.py
tpot/config/classifier.py
tpot/config/classifier_light.py
tpot/config/classifier_mdr.py
tpot/config/classifier_sparse.py
tpot/config/regressor.py
tpot/config/regressor_light.py
tpot/config/regressor_mdr.py
tpot/config/regressor_sparse.py
TPOT_SH-0.9.5.dist-info/LICENSE
TPOT_SH-0.9.5.dist-info/METADATA
TPOT_SH-0.9.5.dist-info/WHEEL
TPOT_SH-0.9.5.dist-info/entry_points.txt
TPOT_SH-0.9.5.dist-info/top_level.txt
TPOT_SH-0.9.5.dist-info/zip-safe
TPOT_SH-0.9.5.dist-info/RECORD
